LICENSE
README.md
setup.py
yyets/__init__.py
yyets.egg-info/PKG-INFO
yyets.egg-info/SOURCES.txt
yyets.egg-info/dependency_links.txt
yyets.egg-info/requires.txt
yyets.egg-info/top_level.txt