Metadata-Version: 2.1
Name: yyets
Version: 1.0.1
Summary: https://yyets.dmesg.app/ wrapper
Home-page: https://github.com/tgbot-collection/YYeTsBot
Author: BennyThink
Author-email: benny.think@gmail.com
License: MIT
Classifier: License :: OSI Approved :: MIT License
Classifier: Programming Language :: Python
Classifier: Programming Language :: Python :: 3
Classifier: Programming Language :: Python :: 3.6
Classifier: Programming Language :: Python :: Implementation :: CPython
Classifier: Programming Language :: Python :: Implementation :: PyPy
Requires-Python: >=3.6.0
License-File: LICENSE
